{"mode":"playing","coordinate_system":"origin at spawn; x positive right, y positive up, z negative is forward","lane_width":18,"lane_depth":2.2,"score":1,"player":{"x":0,"y":0,"z":-2.2},"lane_here":"grass","nearby_lanes":[{"z":-11,"type":"grass","speed":0.98,"traffic_z":null},{"z":-8.8,"type":"river","speed":-1.56,"traffic_z":null},{"z":-6.6,"type":"grass","speed":-1.82,"traffic_z":null},{"z":-4.4,"type":"road","speed":0.98,"traffic_z":-5.02},{"z":-2.2,"type":"grass","speed":1.53,"traffic_z":null},{"z":0,"type":"grass","speed":-1.39,"traffic_z":null},{"z":2.2,"type":"grass","speed":1.65,"traffic_z":null},{"z":4.4,"type":"road","speed":-1.65,"traffic_z":5.02},{"z":6.6,"type":"grass","speed":-1.27,"traffic_z":null}],"movers":[{"type":"car","x":1.98,"z":-5.02,"speed":0.98,"half_x":0.64,"half_z":0.42},{"type":"log","x":-5.4,"z":-8.8,"speed":-1.56,"half_x":1.9,"half_z":0.48}]}